vpmobil/__init__.py
vpmobil/api.py
vpmobil/config.py
vpmobil/models.py
vpmobil/utils.py
vpmobil-2.0.0.dist-info/licenses/LICENSE
vpmobil-2.0.0.dist-info/METADATA
vpmobil-2.0.0.dist-info/WHEEL
vpmobil-2.0.0.dist-info/top_level.txt
vpmobil-2.0.0.dist-info/RECORD
