Metadata-Version: 2.4
Name: vpmobil
Version: 2.0.0
Summary: API wrapper module for evaluating vpmobil substitution plans
Author: Annhilati, Joshi
License-Expression: EUPL-1.2
Project-URL: Homepage, https://github.com/annhilati/vpmobil-py
Project-URL: Documentation, https://annhilati.gitbook.com/vpmobil
Project-URL: Changelog, https://annhilati.gitbook.io/vpmobil/anderes/changelog
Project-URL: Repository, https://github.com/annhilati/vpmobil-py
Project-URL: Bug Tracker, https://github.com/annhilati/vpmobil-py/issues
Project-URL: Download, https://pypi.org/project/vpmobil/
Requires-Python: >=3.8
License-File: LICENSE
Requires-Dist: requests
Requires-Dist: yarl
Requires-Dist: PyPDF2
Dynamic: license-file
